cloudrun/__init__.py
cloudrun/client.py
cloudrun/cloudrun-fs-server
cloudrun/common.py
cloudrun/simplepty.py
cloudrun-0.2.2.dist-info/LICENSE
cloudrun-0.2.2.dist-info/METADATA
cloudrun-0.2.2.dist-info/WHEEL
cloudrun-0.2.2.dist-info/entry_points.txt
cloudrun-0.2.2.dist-info/top_level.txt
cloudrun-0.2.2.dist-info/RECORD
