Metadata-Version: 2.1
Name: cloudrun
Version: 0.2.2
Summary: Client utility for cloudrun.io
Home-page: https://cloudrun.io
Author: The Cloudrun Authors
Author-email: contact@cloudrun.io
License: UNKNOWN
Platform: UNKNOWN
Requires-Dist: requests (>=2.9)
